caasclient/__init__.py
caasclient/client.py
caasclient/exceptions.py
caasclient/http.py
caasclient/shell.py
caasclient/utils.py
caasclient/v1/__init__.py
caasclient/v1/base.py
caasclient/v1/containers.py
caasclient/v1/images.py
caasclient/v1/projects.py
caasclient/v1/shell.py
python_caasclient-1.0.2b1.dist-info/DESCRIPTION.rst
python_caasclient-1.0.2b1.dist-info/METADATA
python_caasclient-1.0.2b1.dist-info/RECORD
python_caasclient-1.0.2b1.dist-info/WHEEL
python_caasclient-1.0.2b1.dist-info/entry_points.txt
python_caasclient-1.0.2b1.dist-info/metadata.json
python_caasclient-1.0.2b1.dist-info/top_level.txt
