Metadata-Version: 2.0
Name: python-caasclient
Version: 1.0.2b1
Summary: Python client for CAAS
Home-page: https://github.com/rogeryu27/python-caasclient
Author: rogeryu
Author-email: roger.leo.yu@gmail.com
License: UNKNOWN
Keywords: client caas
Platform: UNKNOWN
Classifier: Development Status :: 4 - Beta
Classifier: Programming Language :: Python :: 2.7
Requires-Dist: requests (>=2.12)
